LICENSE
README.md
setup.py
bilibili_api/__init__.py
bilibili_api/app.py
bilibili_api/article.py
bilibili_api/audio.py
bilibili_api/bangumi.py
bilibili_api/channel.py
bilibili_api/comment.py
bilibili_api/dynamic.py
bilibili_api/favorite_list.py
bilibili_api/interactive_video.py
bilibili_api/live.py
bilibili_api/requirements.txt
bilibili_api/settings.py
bilibili_api/setup.py
bilibili_api/user.py
bilibili_api/video.py
bilibili_api/data/channel.json
bilibili_api/data/api/README.md
bilibili_api/data/api/app.json
bilibili_api/data/api/article.json
bilibili_api/data/api/audio.json
bilibili_api/data/api/bangumi.json
bilibili_api/data/api/channel.json
bilibili_api/data/api/common.json
bilibili_api/data/api/dynamic.json
bilibili_api/data/api/favorite-list.json
bilibili_api/data/api/interactive_video.json
bilibili_api/data/api/live.json
bilibili_api/data/api/user.json
bilibili_api/data/api/video.json
bilibili_api/example_pkg/__init__.py
bilibili_api/exceptions/ApiException.py
bilibili_api/exceptions/ArgsException.py
bilibili_api/exceptions/CredentialNoBiliJctException.py
bilibili_api/exceptions/CredentialNoBuvid3Exception.py
bilibili_api/exceptions/CredentialNoSessdataException.py
bilibili_api/exceptions/DanmakuClosedException.py
bilibili_api/exceptions/DynamicExceedImagesException.py
bilibili_api/exceptions/LiveException.py
bilibili_api/exceptions/NetworkException.py
bilibili_api/exceptions/ResponseCodeException.py
bilibili_api/exceptions/ResponseException.py
bilibili_api/exceptions/VideoUploadException.py
bilibili_api/exceptions/__init__.py
bilibili_api/utils/AsyncEvent.py
bilibili_api/utils/BytesReader.py
bilibili_api/utils/Credential.py
bilibili_api/utils/Danmaku.py
bilibili_api/utils/__init__.py
bilibili_api/utils/aid_bvid_transformer.py
bilibili_api/utils/network.py
bilibili_api/utils/sync.py
bilibili_api/utils/utils.py
bilibili_api/utils/varint.py
sickooapi.egg-info/PKG-INFO
sickooapi.egg-info/SOURCES.txt
sickooapi.egg-info/dependency_links.txt
sickooapi.egg-info/requires.txt
sickooapi.egg-info/top_level.txt