Metadata-Version: 2.1
Name: sickooapi
Version: 0.0.1
Summary: Test for 魔改
Home-page: https://github.com/Passkou/bilibili-api
Author: Sicko
License: GPLv3+
Keywords: bilibili,api,spider
Platform: UNKNOWN
Classifier: License :: OSI Approved :: GNU General Public License v3 or later (GPLv3+)
Classifier: Natural Language :: Chinese (Simplified)
Classifier: Programming Language :: Python :: 3.8
Classifier: Programming Language :: Python :: 3.9
Requires-Python: >=3.8
